README.rst
setup.py
django_robohash/__init__.py
django_robohash/robotmaker.py
django_robohash/svgparts.py
django_robohash/views.py
django_robohash/templatetags/__init__.py
django_robohash/templatetags/robohash.py
django_robohash_svg.egg-info/PKG-INFO
django_robohash_svg.egg-info/SOURCES.txt
django_robohash_svg.egg-info/dependency_links.txt
django_robohash_svg.egg-info/not-zip-safe
django_robohash_svg.egg-info/requires.txt
django_robohash_svg.egg-info/top_level.txt